{
  "properties": {
    "previous_registry_item": {
      "type": "object",
      "title": "Ранее выданные технические условия",
      "$ref": "http://edoc-schema.kzn.ru/document/ru/uslugi/definitions/date_and_number_tu"
    },
    "object_name": {
      "title": "Наименование объекта",
      "$ref": "http://edoc-schema.kzn.ru/document/ru/uslugi/definitions/string"
    },
    "applicant": {
      "$ref": "http://edoc-schema.kzn.ru/person/ru/applicant",
      "title": "Заявитель"
    },
    "agent": {}
  }
}
