{
  "type": "object",
  "properties": {
    "reject_reasons": {
      "title": "Причина отказа",
      "type": "array",
      "minItems": 1,
      "items": {
        "type": "string",
        "enum": [
          "Другое (указать)",
        ]
      },
      "uniqueItems": true,
    },
    "response_text": {"$ref": "#/definitions/response_text"},
    "attachments": {
      "$ref": "http://edoc-schema.kzn.ru/document/ru/uslugi/definitions/attachments",
      "title": "Доп. приложения"
    },
    "comments": {
      "$ref": "http://edoc-schema.kzn.ru/document/ru/uslugi/definitions/comments",
      "title": "Комментарии"
    }
  }
}