{
  "type": "object",
  "properties": {
    "address_with_map": {
      "$ref": "http://localhost:4000/location/ru/address_with_map",
      "title": "Адрес объекта"
    },
    "organization": {
      "$ref": "http://localhost:4000/organization/ru/organization",
      "title": "Заказчик"
    },
    "agent": {
      "$ref": "http://localhost:4000/person/ru/agent",
      "title": "Представитель"
    },
    "comments": {
      "$ref": "http://localhost:4000/document/ru/uslugi/definitions/comments",
      "title": "Комментарии"
    }
  }
}
