{
  "id": "http://edoc-schema.kzn.ru/document/ru/uslugi/definitions/facades_2",
  "$schema": "http://json-schema.org/draft-06/schema#",
  "type": "array",
  "title": "Фасады",
  "minItems": 1,
  "items": {
    "type": "object",
    "properties": {
      "facade_type": {
        "type": "string",
        "title": "Тип фасада",
        "enum": [
          "главный",
          "левый",
          "правый",
          "боковой",
          "дворовой",
          "иное"
        ]
      },
      "image_original": {
        "$ref": "http://edoc-schema.kzn.ru/document/ru/uslugi/definitions/image_original",
        "title": "Эскизное предложение",
        "description": ""
      },
      "facade_elements": {
        "type": "array",
        "title": "Пояснительная записка",
        "minItems": 1,
        "items": {
          "type": "object",
          "properties": {
            "environmental_construction_type": {
              "$ref": "http://edoc-schema.kzn.ru/document/ru/uslugi/definitions/environmental_construction_type",
              "title": "Элемент фасада"
            },
            "color": {
              "type": "string",
              "title": "Укажите наиболее близкий цвет"
            },
            "description": {
              "type": "string",
              "title": "Описание"
            },
            "material": {
              "type": "string",
              "title": "Материал"
            },
            "color_description": {
              "type": "string",
              "title": "Описание цвета (с указанием системы: RAL, NCS и т.п.)"
            }
          }
        }
      }
    }
  }
}
